examples/__init__.py
examples/functions_analytic_examples.py
examples/functions_numeric_examples.py
examples/run_analytic_examples.py
examples/run_numeric_examples.py
python2/__init__.py
python2/inputs_simulation.py
python2/magnetisations.py
python2/propertyfunctions.py
python2/routines_analytic.py
python2/routines_test.py
python2/shell_commands.py
python2/spinD_kiel_jobs.py
python2/visualizations.py
python3/__init__.py
python3/constants.py
python3/inputs_simulation.py
python3/magnetisations.py
python3/propertyfunctions.py
python3/routines_analytic.py
python3/shell_commands.py
python3/spinD_kiel_jobs.py
python3/testsignatures.py
python3/visualizations.py
python3/analyze/__init__.py
python3/analyze/localextrema/__init__.py
python3/analyze/localextrema/cfindlocalextrema.py
python3/analyze/multilayer/__init__.py
python3/analyze/multilayer/cdiffbetweenlayers.py
python3/ioutils/__init__.py
python3/ioutils/loading_utilities.py
python3/ioutils/writing_utilities.py
python3/write_inputs/__init__.py
python3/write_inputs/cinvert_eigenvector.py
python3/write_inputs/cwrite_inputs.py
tests/__init__.py
tests/ianalyze.py
tests/itest.py
tests/test_modefollowing/__init__.py
tests/test_modefollowing/test_modefollowing.py
tests/test_modefollowing/test_mf_fm/__init__.py
tests/test_modefollowing/test_mf_fm/canalyze_fm_modes.py
tests/test_modefollowing/test_mf_fm/ctest_fm_modes.py
tests/test_multilayers/__init__.py
tests/test_multilayers/ianalyze.py
tests/test_multilayers/itest.py
tests/test_multilayers/test_multilayers.py
tests/test_multilayers/test_precission_withoutdamping/__init__.py
tests/test_multilayers/test_precission_withoutdamping/canalyzeprecisionwithoutdamping.py
tests/test_multilayers/test_precission_withoutdamping/ctestprecisionwithoutdamping.py
tests/test_single_spin_precission/__init__.py
tests/test_single_spin_precission/test_precission.py
tests/test_spinspiral_dispersion/__init__.py
tests/test_spinspiral_dispersion/test_spinspiral_dispersion.py
userlib_spinD-0.0.43.dist-info/LICENSE
userlib_spinD-0.0.43.dist-info/METADATA
userlib_spinD-0.0.43.dist-info/WHEEL
userlib_spinD-0.0.43.dist-info/top_level.txt
userlib_spinD-0.0.43.dist-info/RECORD
