Metadata-Version: 2.1
Name: userlib-spinD
Version: 0.0.43
Summary: userlibrary functions for using SpinD-code of the spintronics group in Kiel
Home-page: https://gitlab.com/hschrautzer/seafood
Author: Moritz Goerzen
Author-email: h.schrautzer@gmx.de
License: UNKNOWN
Platform: UNKNOWN
Classifier: Programming Language :: Python :: 3
Classifier: License :: OSI Approved :: MIT License
Classifier: Operating System :: OS Independent
Requires-Python: >=3.6
